langchain_tensorlake/__init__.py
langchain_tensorlake/tensorlake_tool.py
langchain_tensorlake-0.1.7.dist-info/licenses/LICENSE
langchain_tensorlake-0.1.7.dist-info/METADATA
langchain_tensorlake-0.1.7.dist-info/WHEEL
langchain_tensorlake-0.1.7.dist-info/top_level.txt
langchain_tensorlake-0.1.7.dist-info/RECORD
