Metadata-Version: 2.4
Name: langchain-tensorlake
Version: 0.1.7
Summary: A LangChain tool for parsing documents using Tensorlake's DocumentAI.
License: MIT
Project-URL: Homepage, https://github.com/tensorlakeai/langchain-tensorlake
License-File: LICENSE
Requires-Dist: langchain
Requires-Dist: langgraph
Requires-Dist: langchain-openai
Requires-Dist: pydantic
Requires-Dist: python-dotenv
Requires-Dist: tensorlake
Dynamic: license-file
